CHANGELOG.txt
LICENSE.txt
MANIFEST.in
README.md
setup.py
ScsLabs2.egg-info/PKG-INFO
ScsLabs2.egg-info/SOURCES.txt
ScsLabs2.egg-info/dependency_links.txt
ScsLabs2.egg-info/requires.txt
ScsLabs2.egg-info/top_level.txt
env/bin/rst2html.py
env/bin/rst2html4.py
env/bin/rst2html5.py
env/bin/rst2latex.py
env/bin/rst2man.py
env/bin/rst2odt.py
env/bin/rst2odt_prepstyles.py
env/bin/rst2pseudoxml.py
env/bin/rst2s5.py
env/bin/rst2xetex.py
env/bin/rst2xml.py
env/bin/rstpep2html.py
env/lib/python3.9/site-packages/easy_install.py
env/lib/python3.9/site-packages/six.py
env/lib/python3.9/site-packages/zipp.py
env/lib/python3.9/site-packages/Pygments-2.11.2.dist-info/entry_points.txt
env/lib/python3.9/site-packages/Pygments-2.11.2.dist-info/top_level.txt
env/lib/python3.9/site-packages/SecretStorage-3.3.1.dist-info/top_level.txt
env/lib/python3.9/site-packages/bleach/__init__.py
env/lib/python3.9/site-packages/bleach/callbacks.py
env/lib/python3.9/site-packages/bleach/html5lib_shim.py
env/lib/python3.9/site-packages/bleach/linkifier.py
env/lib/python3.9/site-packages/bleach/sanitizer.py
env/lib/python3.9/site-packages/bleach/utils.py
env/lib/python3.9/site-packages/bleach-4.1.0.dist-info/top_level.txt
env/lib/python3.9/site-packages/bleach/_vendor/__init__.py
env/lib/python3.9/site-packages/bleach/_vendor/parse.py
env/lib/python3.9/site-packages/bleach/_vendor/vendor.txt
env/lib/python3.9/site-packages/bleach/_vendor/html5lib/__init__.py
env/lib/python3.9/site-packages/bleach/_vendor/html5lib/_ihatexml.py
env/lib/python3.9/site-packages/bleach/_vendor/html5lib/_inputstream.py
env/lib/python3.9/site-packages/bleach/_vendor/html5lib/_tokenizer.py
env/lib/python3.9/site-packages/bleach/_vendor/html5lib/_utils.py
env/lib/python3.9/site-packages/bleach/_vendor/html5lib/constants.py
env/lib/python3.9/site-packages/bleach/_vendor/html5lib/html5parser.py
env/lib/python3.9/site-packages/bleach/_vendor/html5lib/serializer.py
env/lib/python3.9/site-packages/bleach/_vendor/html5lib-1.1.dist-info/top_level.txt
env/lib/python3.9/site-packages/bleach/_vendor/html5lib/_trie/__init__.py
env/lib/python3.9/site-packages/bleach/_vendor/html5lib/_trie/_base.py
env/lib/python3.9/site-packages/bleach/_vendor/html5lib/_trie/py.py
env/lib/python3.9/site-packages/bleach/_vendor/html5lib/filters/__init__.py
env/lib/python3.9/site-packages/bleach/_vendor/html5lib/filters/alphabeticalattributes.py
env/lib/python3.9/site-packages/bleach/_vendor/html5lib/filters/base.py
env/lib/python3.9/site-packages/certifi-2021.10.8.dist-info/top_level.txt
env/lib/python3.9/site-packages/cffi-1.15.0.dist-info/entry_points.txt
env/lib/python3.9/site-packages/cffi-1.15.0.dist-info/top_level.txt
env/lib/python3.9/site-packages/charset_normalizer-2.0.12.dist-info/entry_points.txt
env/lib/python3.9/site-packages/charset_normalizer-2.0.12.dist-info/top_level.txt
env/lib/python3.9/site-packages/colorama-0.4.4.dist-info/LICENSE.txt
env/lib/python3.9/site-packages/colorama-0.4.4.dist-info/top_level.txt
env/lib/python3.9/site-packages/cryptography-36.0.1.dist-info/top_level.txt
env/lib/python3.9/site-packages/docutils-0.18.1.dist-info/COPYING.txt
env/lib/python3.9/site-packages/docutils-0.18.1.dist-info/top_level.txt
env/lib/python3.9/site-packages/idna-3.3.dist-info/LICENSE.md
env/lib/python3.9/site-packages/idna-3.3.dist-info/top_level.txt
env/lib/python3.9/site-packages/importlib_metadata-4.11.2.dist-info/top_level.txt
env/lib/python3.9/site-packages/keyring-23.5.0.dist-info/entry_points.txt
env/lib/python3.9/site-packages/keyring-23.5.0.dist-info/top_level.txt
env/lib/python3.9/site-packages/packaging-21.3.dist-info/top_level.txt
env/lib/python3.9/site-packages/pip-20.3.4.dist-info/LICENSE.txt
env/lib/python3.9/site-packages/pip-20.3.4.dist-info/entry_points.txt
env/lib/python3.9/site-packages/pip-20.3.4.dist-info/top_level.txt
env/lib/python3.9/site-packages/pkg_resources-0.0.0.dist-info/AUTHORS.txt
env/lib/python3.9/site-packages/pkg_resources-0.0.0.dist-info/LICENSE.txt
env/lib/python3.9/site-packages/pkginfo-1.8.2.dist-info/LICENSE.txt
env/lib/python3.9/site-packages/pkginfo-1.8.2.dist-info/entry_points.txt
env/lib/python3.9/site-packages/pkginfo-1.8.2.dist-info/top_level.txt
env/lib/python3.9/site-packages/pycparser-2.21.dist-info/top_level.txt
env/lib/python3.9/site-packages/pyparsing-3.0.7.dist-info/top_level.txt
env/lib/python3.9/site-packages/readme_renderer-32.0.dist-info/entry_points.txt
env/lib/python3.9/site-packages/readme_renderer-32.0.dist-info/top_level.txt
env/lib/python3.9/site-packages/requests-2.27.1.dist-info/top_level.txt
env/lib/python3.9/site-packages/requests_toolbelt-0.9.1.dist-info/top_level.txt
env/lib/python3.9/site-packages/rfc3986-2.0.0.dist-info/top_level.txt
env/lib/python3.9/site-packages/setuptools-44.1.1.dist-info/AUTHORS.txt
env/lib/python3.9/site-packages/setuptools-44.1.1.dist-info/LICENSE.txt
env/lib/python3.9/site-packages/setuptools-44.1.1.dist-info/dependency_links.txt
env/lib/python3.9/site-packages/setuptools-44.1.1.dist-info/entry_points.txt
env/lib/python3.9/site-packages/setuptools-44.1.1.dist-info/top_level.txt
env/lib/python3.9/site-packages/six-1.16.0.dist-info/top_level.txt
env/lib/python3.9/site-packages/tqdm-4.63.0.dist-info/entry_points.txt
env/lib/python3.9/site-packages/tqdm-4.63.0.dist-info/top_level.txt
env/lib/python3.9/site-packages/twine-3.8.0.dist-info/entry_points.txt
env/lib/python3.9/site-packages/twine-3.8.0.dist-info/top_level.txt
env/lib/python3.9/site-packages/urllib3-1.26.8.dist-info/LICENSE.txt
env/lib/python3.9/site-packages/urllib3-1.26.8.dist-info/top_level.txt
env/lib/python3.9/site-packages/webencodings-0.5.1.dist-info/top_level.txt
env/lib/python3.9/site-packages/zipp-3.7.0.dist-info/top_level.txt
env/lib64/python3.9/site-packages/Pygments-2.11.2.dist-info/entry_points.txt
env/lib64/python3.9/site-packages/Pygments-2.11.2.dist-info/top_level.txt
env/lib64/python3.9/site-packages/SecretStorage-3.3.1.dist-info/top_level.txt
