Metadata-Version: 2.1
Name: ScsLabs2
Version: 0.0.1
Summary: ScsLabs adalah modul edukasi untuk Pemula / Expert.
Home-page: https://github.com/SkullCyberSecurity/ScsLabs
Author: TomsDroid
Author-email: tomsdroid@kingeagle.tech
License: MIT
Keywords: scs,skullcybersecurity,whois-domain,whois
Platform: UNKNOWN
Classifier: Development Status :: 1 - Planning
Classifier: Intended Audience :: Education
Classifier: Operating System :: Unix
Classifier: Operating System :: MacOS :: MacOS X
Classifier: Operating System :: Microsoft :: Windows
Classifier: License :: OSI Approved :: MIT License
Classifier: Programming Language :: Python :: 3
